krezy/__init__.py
krezy/detector.py
krezy/version.py
krezy/desktop/__init__.py
krezy/desktop/app.py
krezy/mobile/__init__.py
krezy/mobile/app.py
krezy/web/__init__.py
krezy/web/app.py
krezy-1.0.0.dist-info/METADATA
krezy-1.0.0.dist-info/WHEEL
krezy-1.0.0.dist-info/entry_points.txt
krezy-1.0.0.dist-info/top_level.txt
krezy-1.0.0.dist-info/RECORD
