Metadata-Version: 2.1
Name: krezy
Version: 1.0.0
Summary: A powerful cross-platform emotion detection library
Home-page: https://github.com/itsaakif/krezy
Author: Aakif Mudel
Author-email: aakifmudel@gmail.com
Project-URL: Bug Tracker, https://github.com/itsaakif/krezy/issues
Project-URL: Documentation, https://krezy.readthedocs.io/
Classifier: Development Status :: 5 - Production/Stable
Classifier: Intended Audience :: Developers
Classifier: Topic :: Software Development :: Libraries :: Python Modules
Classifier: Topic :: Scientific/Engineering :: Image Recognition
Classifier: License :: OSI Approved :: MIT License
Classifier: Programming Language :: Python :: 3
Classifier: Programming Language :: Python :: 3.7
Classifier: Programming Language :: Python :: 3.8
Classifier: Programming Language :: Python :: 3.9
Classifier: Programming Language :: Python :: 3.10
Classifier: Operating System :: OS Independent
Requires-Python: >=3.7
Requires-Dist: deepface>=0.0.79
Requires-Dist: opencv-python>=4.7.0
Requires-Dist: numpy>=1.21.0
Requires-Dist: pandas>=1.3.0
Provides-Extra: web
Requires-Dist: Flask>=2.0.0; extra == "web"
Requires-Dist: Flask-SocketIO>=5.0.0; extra == "web"
Provides-Extra: mobile
Requires-Dist: kivy>=2.1.0; extra == "mobile"
Provides-Extra: desktop
Requires-Dist: customtkinter>=5.1.2; extra == "desktop"
Provides-Extra: all
Requires-Dist: Flask>=2.0.0; extra == "all"
Requires-Dist: Flask-SocketIO>=5.0.0; extra == "all"
Requires-Dist: kivy>=2.1.0; extra == "all"
Requires-Dist: customtkinter>=5.1.2; extra == "all"
